openinference/instrumentation/google_adk/__init__.py
openinference/instrumentation/google_adk/_wrappers.py
openinference/instrumentation/google_adk/py.typed
openinference/instrumentation/google_adk/version.py
openinference_instrumentation_google_adk-0.1.8.dist-info/METADATA
openinference_instrumentation_google_adk-0.1.8.dist-info/WHEEL
openinference_instrumentation_google_adk-0.1.8.dist-info/entry_points.txt
openinference_instrumentation_google_adk-0.1.8.dist-info/licenses/LICENSE
openinference_instrumentation_google_adk-0.1.8.dist-info/RECORD
